{"child_modules": [], "data_mtime": 1535895719, "dep_lines": [4, 5, 6, 1, 1, 1, 1, 2, 3, 8, 9], "dep_prios": [10, 5, 10, 5, 30, 30, 10, 10, 10, 5, 5], "dependencies": ["attr", "attr.validators", "pathlib", "builtins", "abc", "typing"], "deps_mtime": null, "hash": "05bd94007c0d79bce22fb9aaac825530", "id": "ca_analysis.single_fov_analysis", "ignore_all": false, "interface_hash": "489932b2ebf461a031de099c6798cc03", "mtime": 1535532087, "options": {"always_false": [], "always_true": [], "bazel": false, "check_untyped_defs": false, "disallow_any_decorated": false, "disallow_any_explicit": false, "disallow_any_expr": false, "disallow_any_generics": false, "disallow_any_unimported": false, "disallow_subclassing_any": false, "disallow_untyped_calls": false, "disallow_untyped_decorators": false, "disallow_untyped_defs": false, "follow_imports": "silent", "follow_imports_for_stubs": false, "ignore_errors": false, "ignore_missing_imports": true, "local_partial_types": false, "no_implicit_optional": false, "platform": "linux", "quick_and_dirty": false, "show_none_errors": true, "strict_boolean": false, "strict_optional": true, "strict_optional_whitelist": null, "warn_no_return": true, "warn_return_any": false, "warn_unused_ignores": false}, "path": "/state/partition1/home/pblab/data/MatlabCode/PBLabToolkit/CalciumDataAnalysis/python-ca-analysis-bloodflow/ca_analysis/single_fov_analysis.py", "size": 3387, "suppressed": ["numpy", "pandas", "xarray", "analog_trace", "fluo_metadata"], "version_id": "0.620"}
